koaeda/AEDA.py
koaeda/__init__.py
koaeda-0.0.6.dist-info/LICENSE
koaeda-0.0.6.dist-info/METADATA
koaeda-0.0.6.dist-info/WHEEL
koaeda-0.0.6.dist-info/top_level.txt
koaeda-0.0.6.dist-info/RECORD
