Metadata-Version: 2.1
Name: koaeda
Version: 0.0.6
Summary: Using Korean Language A Easier Data Augmentation
Home-page: https://github.com/Kangsukmin/KoAEDA
Author: decyma
Author-email: soos3121@gmail.com
License: MIT
Platform: UNKNOWN
Classifier: Programming Language :: Python :: 3
Classifier: License :: OSI Approved :: MIT License
Classifier: Operating System :: OS Independent
Requires-Python: >=3.6
License-File: LICENSE
